MANIFEST.in
README.txt
setup.cfg
setup.py
docs/HISTORY.txt
docs/INSTALL.txt
docs/LICENSE.GPL
docs/LICENSE.txt
ploomcake/__init__.py
ploomcake/__init__.pyc
ploomcake.pa.egg-info/PKG-INFO
ploomcake.pa.egg-info/SOURCES.txt
ploomcake.pa.egg-info/dependency_links.txt
ploomcake.pa.egg-info/entry_points.txt
ploomcake.pa.egg-info/namespace_packages.txt
ploomcake.pa.egg-info/not-zip-safe
ploomcake.pa.egg-info/requires.txt
ploomcake.pa.egg-info/top_level.txt
ploomcake/pa/__init__.py
ploomcake/pa/configure.zcml
ploomcake/pa/install_util.py
ploomcake/pa/setuphandlers.py
ploomcake/pa/tests.py
ploomcake/pa/browser/__init__.py
ploomcake/pa/browser/configure.zcml
ploomcake/pa/browser/resources/style.css
ploomcake/pa/profiles/default/actions.xml
ploomcake/pa/profiles/default/cssregistry.xml
ploomcake/pa/profiles/default/metadata.xml
ploomcake/pa/profiles/default/registry.xml