Metadata-Version: 1.0
Name: ploomcake.pa
Version: 0.1
Summary: A policy product for Italian PA
Home-page: https://github.com/ploomcake/ploomcake.pa
Author: Maurizio Lupo
Author-email: maurizio.lupo@redomino.com
License: GPL
Platform: UNKNOWN
Classifier: Framework :: Plone
Classifier: Programming Language :: Python
